stix_shifter_modules/sumologic/__init__.py
stix_shifter_modules/sumologic/entry_point.py
stix_shifter_modules/sumologic/configuration/config.json
stix_shifter_modules/sumologic/configuration/dialects.json
stix_shifter_modules/sumologic/configuration/lang_en.json
stix_shifter_modules/sumologic/stix_translation/__init__.py
stix_shifter_modules/sumologic/stix_translation/json_to_stix_translator.py
stix_shifter_modules/sumologic/stix_translation/query_constructor.py
stix_shifter_modules/sumologic/stix_translation/query_translator.py
stix_shifter_modules/sumologic/stix_translation/json/cloud_siem_from_stix_map.json
stix_shifter_modules/sumologic/stix_translation/json/cloud_siem_to_stix_map.json
stix_shifter_modules/sumologic/stix_translation/json/from_stix_map.json
stix_shifter_modules/sumologic/stix_translation/json/operators.json
stix_shifter_modules/sumologic/stix_translation/json/to_stix_map.json
stix_shifter_modules/sumologic/stix_transmission/__init__.py
stix_shifter_modules/sumologic/stix_transmission/api_client.py
stix_shifter_modules/sumologic/stix_transmission/delete_connector.py
stix_shifter_modules/sumologic/stix_transmission/error_mapper.py
stix_shifter_modules/sumologic/stix_transmission/ping_connector.py
stix_shifter_modules/sumologic/stix_transmission/query_connector.py
stix_shifter_modules/sumologic/stix_transmission/results_connector.py
stix_shifter_modules/sumologic/stix_transmission/status_connector.py
stix_shifter_modules_sumologic-8.0.2.dist-info/licenses/AUTHORS.md
stix_shifter_modules_sumologic-8.0.2.dist-info/licenses/LICENSE.md
stix_shifter_modules_sumologic-8.0.2.dist-info/licenses/NOTICE
stix_shifter_modules_sumologic-8.0.2.dist-info/METADATA
stix_shifter_modules_sumologic-8.0.2.dist-info/WHEEL
stix_shifter_modules_sumologic-8.0.2.dist-info/top_level.txt
stix_shifter_modules_sumologic-8.0.2.dist-info/RECORD
